{"cameraMode":{"drawMode":0,"name":"Shaded","section":"Shading Mode"},"sceneLighting":true,"audioPlay":false,"sceneViewState":{"m_AlwaysRefresh":false,"showFog":true,"showSkybox":true,"showFlares":true,"showImageEffects":true,"showParticleSystems":true,"showVisualEffectGraphs":true,"m_FxEnabled":true},"in2DMode":false,"pivot":{"x":965.0234375,"y":600.9425659179688,"z":23.53759765625},"rotation":{"x":0.013498430140316487,"y":0.010796897113323212,"z":0.00015206605894491076,"w":-0.9998692870140076},"size":604.1417236328125,"orthographic":false}